husein_boilerplate/__init__.py
husein_boilerplate/multiprocessing.py
husein_boilerplate/rules.py
husein_boilerplate-0.0.5.dist-info/METADATA
husein_boilerplate-0.0.5.dist-info/WHEEL
husein_boilerplate-0.0.5.dist-info/top_level.txt
husein_boilerplate-0.0.5.dist-info/RECORD
