Metadata-Version: 2.1
Name: husein-boilerplate
Version: 0.0.5
Summary: Boilerplate for Husein
Home-page: https://github.com/huseinzol05/husein-boilerplate
Author: huseinzol05
Author-email: husein.zol05@gmail.com
License: MIT
Platform: UNKNOWN
Classifier: Programming Language :: Python :: 3.7
Classifier: Intended Audience :: Developers
Classifier: License :: OSI Approved :: MIT License
Classifier: Operating System :: OS Independent
Requires-Python: >=3.6.*
Requires-Dist: emoji
Requires-Dist: gensim
